odoo/addons/stock_customer_deposit_sale_margin/README.rst
odoo/addons/stock_customer_deposit_sale_margin/__init__.py
odoo/addons/stock_customer_deposit_sale_margin/__manifest__.py
odoo/addons/stock_customer_deposit_sale_margin/i18n/es.po
odoo/addons/stock_customer_deposit_sale_margin/i18n/it.po
odoo/addons/stock_customer_deposit_sale_margin/i18n/stock_customer_deposit_sale_margin.pot
odoo/addons/stock_customer_deposit_sale_margin/models/__init__.py
odoo/addons/stock_customer_deposit_sale_margin/models/sale_order_line.py
odoo/addons/stock_customer_deposit_sale_margin/readme/CONTEXT.md
odoo/addons/stock_customer_deposit_sale_margin/readme/CONTRIBUTORS.md
odoo/addons/stock_customer_deposit_sale_margin/readme/DESCRIPTION.md
odoo/addons/stock_customer_deposit_sale_margin/readme/USAGE.md
odoo/addons/stock_customer_deposit_sale_margin/static/description/icon.png
odoo/addons/stock_customer_deposit_sale_margin/static/description/index.html
odoo/addons/stock_customer_deposit_sale_margin/tests/__init__.py
odoo/addons/stock_customer_deposit_sale_margin/tests/test_stock_customer_deposit_sale_margin.py
odoo_addon_stock_customer_deposit_sale_margin-16.0.1.0.2.dist-info/METADATA
odoo_addon_stock_customer_deposit_sale_margin-16.0.1.0.2.dist-info/WHEEL
odoo_addon_stock_customer_deposit_sale_margin-16.0.1.0.2.dist-info/top_level.txt
odoo_addon_stock_customer_deposit_sale_margin-16.0.1.0.2.dist-info/RECORD
