Metadata-Version: 2.1
Name: odoo-addon-stock_customer_deposit_sale_margin
Version: 16.0.1.0.2
Summary: Set purchase price to zero when deliver customer deposit
Home-page: https://github.com/OCA/stock-logistics-workflow
Author: Moduon, Odoo Community Association (OCA)
Author-email: support@odoo-community.org
License: LGPL-3
Classifier: Programming Language :: Python
Classifier: Framework :: Odoo
Classifier: Framework :: Odoo :: 16.0
Classifier: License :: OSI Approved :: GNU Lesser General Public License v3 (LGPLv3)
Classifier: Development Status :: 3 - Alpha
Requires-Python: >=3.10
Requires-Dist: odoo-addon-stock-customer-deposit<16.1dev,>=16.0dev
Requires-Dist: odoo<16.1dev,>=16.0a
